<?xml version="1.0" encoding="UTF-8"?>
<actions>
        <action>
            <actionName>CUSTOM-deploy-prod</actionName>
            <displayName>deploy-prod</displayName>
            <goals>
                <goal>deploy</goal>
            </goals>
            <activatedProfiles>
                <activatedProfile>profile-production</activatedProfile>
            </activatedProfiles>
        </action>
        <action>
            <actionName>CUSTOM-deploy-test</actionName>
            <displayName>deploy-test</displayName>
            <goals>
                <goal>deploy</goal>
            </goals>
            <activatedProfiles>
                <activatedProfile>profile-test</activatedProfile>
            </activatedProfiles>
        </action>
        <action>
            <actionName>CUSTOM-deploy</actionName>
            <displayName>deploy</displayName>
            <goals>
                <goal>clean</goal>
                <goal>deploy</goal>
            </goals>
        </action>
    </actions>
